{
  "version": "3.73.30119.0",
  "course_id": "5cgkYGOjiAR",
  "title": "Microsoft Word and Accessibility Best Practices",
  "thumbnail": "story_content/thumbnail.jpg",
  "scenes": [
    {
      "title": "Main Block"
    }
  ],
  "slides": [
    {
      "id": "6qUYEqtWskp",
      "title": "Certification",
      "scene_index": "1.1"
    },
    {
      "id": "5rkawftkqtB",
      "title": "Acknowledgment",
      "scene_index": "1.2"
    }
  ],
  "player": {
    "name": "unified",
    "width": 980,
    "height": 634
  },
  "stage": {
    "width": 720,
    "height": 540
  }
}